{
  "expectations": [
    {
      "text": "Output file uses CSF3 format with 'satisfies Meta<typeof Button>'",
      "passed": false,
      "evidence": "Not found: satisfies Meta<typeof Button>"
    },
    {
      "text": "Meta has tags: ['autodocs'] and layout: 'fullscreen'",
      "passed": false,
      "evidence": "autodocs=yes, fullscreen=no"
    },
    {
      "text": "All 5 sentiments from types file appear in a story",
      "passed": false,
      "evidence": "All sentiments present=True, story export=False"
    },
    {
      "text": "All 3 emphasis levels appear in a story",
      "passed": false,
      "evidence": "All emphases present=True, story export=False"
    },
    {
      "text": "All 5 sizes appear in a story",
      "passed": true,
      "evidence": "All sizes present=True, story export=True"
    },
    {
      "text": "All 5 states appear in a story",
      "passed": true,
      "evidence": "All states present=True, story export=True"
    },
    {
      "text": "Token table extracts CSS custom properties from the CSS file \u2014 not invented values",
      "passed": true,
      "evidence": "Token data=True, token story=True"
    },
    {
      "text": "Anatomy matches the JSX structure (btn root, btn__prefix, btn__label, btn__suffix, btn__spinner)",
      "passed": true,
      "evidence": "Found 4/4 anatomy elements, story=True"
    },
    {
      "text": "Uses DosDonts helper for usage guidance",
      "passed": true,
      "evidence": "Usage story=True, uses helper/pattern=True"
    },
    {
      "text": "Structure dimension is represented (standard, icon-only, split)",
      "passed": true,
      "evidence": "All structures present=True"
    },
    {
      "text": "No hardcoded color or spacing values",
      "passed": false,
      "evidence": "Found 6 hardcoded color values in render code"
    }
  ],
  "summary": {
    "passed": 6,
    "failed": 5,
    "total": 11,
    "pass_rate": 0.55
  }
}